predpy/__init__.py
predpy/autoregression.py
predpy/cleandata.py
predpy/galgraphs.py
predpy/predpy.py
predpy/ridge_regression.py
predpy/timeseries.py
predpy-0.0.6.dist-info/METADATA
predpy-0.0.6.dist-info/RECORD
predpy-0.0.6.dist-info/WHEEL
predpy-0.0.6.dist-info/dependency_links.txt
predpy-0.0.6.dist-info/top_level.txt
