Metadata-Version: 2.1
Name: predpy
Version: 0.0.6
Summary: Series of Data Science Graphs written by Philip Geurin and Matt Drury
Home-page: https://github.com/pgeurin/predpy
Author: Philip Geurin and Matt Drury
Author-email: philip.geurin@gmail.com
License: BSD
Keywords: statistics,data,science,datascience
Platform: UNKNOWN
Classifier: Development Status :: 3 - Alpha
Classifier: Intended Audience :: Developers
Classifier: Intended Audience :: Education
Classifier: Intended Audience :: Science/Research
Classifier: License :: OSI Approved :: BSD License
Classifier: Programming Language :: Python :: 3
Classifier: Programming Language :: Python :: 3.3
Classifier: Programming Language :: Python :: 3.4
Classifier: Programming Language :: Python :: 3.5
Classifier: Programming Language :: Python :: 3.6
Classifier: Topic :: Scientific/Engineering
Classifier: Topic :: Scientific/Engineering :: Mathematics
Requires-Dist: numpy
Requires-Dist: pandas
Requires-Dist: scikit-learn
Requires-Dist: matplotlib
Requires-Dist: scipy
Requires-Dist: basis-expansions
Requires-Dist: regression-tools
Requires-Dist: stringcase
Requires-Dist: tqdm
